llnl_sina-1.15.1.dist-info/licenses/LICENSE
sina/__init__.py
sina/dao.py
sina/datastore.py
sina/model.py
sina/postprocessing.py
sina/proxies.py
sina/sjson.py
sina/utils.py
sina/visualization.py
sina/cli/__init__.py
sina/cli/diff.py
sina/cli/driver.py
sina/datastores/__init__.py
sina/datastores/cass.py
sina/datastores/cass_schema.py
sina/datastores/sql.py
sina/datastores/sql_schema.py
tests/__init__.py
tests/backend_test.py
tests/cass_test.py
tests/datastore_test.py
tests/integration_test.py
tests/jupyter_test.py
tests/model_proxy_test.py
tests/model_test.py
tests/mysql_test.py
tests/orm_test.py
tests/postprocessing_test.py
tests/sqlite_test.py
tests/utils_test.py
tests/cli/__init__.py
tests/cli/diff_test.py
tests/cli/driver_test.py
tests/run_tests/__init__.py
tests/run_tests/notebooks/__init__.py
tests/run_tests/notebooks/test_basic_usage.ipynb.py
tests/run_tests/notebooks/test_getting_started.ipynb.py
tests/run_tests/notebooks/test_post_processing.ipynb.py
tests/run_tests/notebooks/test_relationships.ipynb.py
tests/run_tests/notebooks/test_vis_usage.ipynb.py
tests/run_tests/notebooks/test_working_with_records.ipynb.py
tests/sql/__init__.py
llnl_sina-1.15.1.dist-info/METADATA
llnl_sina-1.15.1.dist-info/WHEEL
llnl_sina-1.15.1.dist-info/entry_points.txt
llnl_sina-1.15.1.dist-info/top_level.txt
llnl_sina-1.15.1.dist-info/RECORD
