Metadata-Version: 2.4
Name: llnl-sina
Version: 1.15.1
Summary: Simulation INsight and Analysis
Author: Siboka Team
Author-email: weave-support@llnl.gov
License: MIT
Classifier: Development Status :: 5 - Production/Stable
Classifier: License :: OSI Approved :: MIT License
Classifier: Programming Language :: Python :: 3
Classifier: Programming Language :: Python :: 3.6
Classifier: Programming Language :: Python :: 3.7
License-File: LICENSE
Requires-Dist: six
Requires-Dist: sqlalchemy
Requires-Dist: sqlalchemy<2; python_version < "3"
Requires-Dist: enum34; python_version < "3.4"
Requires-Dist: orjson; python_version >= "3.6" and platform_machine != "ppc64le"
Requires-Dist: ujson; python_version >= "3.6" and platform_machine == "ppc64le"
Requires-Dist: ujson<4; python_version < "3.6" and platform_machine != "ppc64le"
Requires-Dist: freetype-py; platform_system == "Darwin"
Provides-Extra: cassandra
Requires-Dist: cassandra-driver; extra == "cassandra"
Provides-Extra: jupyter
Requires-Dist: jupyter-client; extra == "jupyter"
Requires-Dist: ipython<8.13; extra == "jupyter"
Requires-Dist: ipykernel; extra == "jupyter"
Requires-Dist: ipywidgets; extra == "jupyter"
Requires-Dist: matplotlib; extra == "jupyter"
Requires-Dist: tabulate; extra == "jupyter"
Provides-Extra: cli-tools
Requires-Dist: deepdiff; extra == "cli-tools"
Requires-Dist: texttable; extra == "cli-tools"
Provides-Extra: mysql
Requires-Dist: mysql-connector-python; extra == "mysql"
Dynamic: author
Dynamic: author-email
Dynamic: classifier
Dynamic: description
Dynamic: license
Dynamic: license-file
Dynamic: provides-extra
Dynamic: requires-dist
Dynamic: summary
